ecr_cleaner/__init__.py
ecr_cleaner/ecr_cleaner.py
ecr_cleaner/helpers.py
ecr_cleaner/resources/.keep
ecr_cleaner_cli/__init__.py
ecr_cleaner_cli/cli.py
ecr_cleaner_cli/resources/.keep
ecr_cleaner-0.1.11.dist-info/METADATA
ecr_cleaner-0.1.11.dist-info/WHEEL
ecr_cleaner-0.1.11.dist-info/entry_points.txt
ecr_cleaner-0.1.11.dist-info/licenses/LICENSE
ecr_cleaner-0.1.11.dist-info/RECORD
