Metadata-Version: 2.3
Name: ecr_cleaner
Version: 0.1.11
Summary: ECR Image Cleanup Tool
Project-URL: Bug reports, https://github.com/rahulinux/ecr-cleaner/issues/new
Project-URL: Documentation, https://github.com/rahulinux/ecr-cleaner/blob/main/python/README.md
Project-URL: Source, https://github.com/rahulinux/ecr-cleaner
Author-email: Rahul Patil <4476687+rahulinux@users.noreply.github.com>
License-Expression: Apache-2.0
License-File: LICENSE
Keywords: aws,cleanup,ecr,package,python
Classifier: Development Status :: 4 - Beta
Classifier: Intended Audience :: Developers
Classifier: License :: OSI Approved :: Apache Software License
Classifier: Natural Language :: English
Classifier: Programming Language :: Python :: 3
Classifier: Programming Language :: Python :: 3.9
Classifier: Programming Language :: Python :: 3.10
Classifier: Programming Language :: Python :: 3.11
Classifier: Programming Language :: Python :: 3.12
Requires-Python: >=3.9
Requires-Dist: boto3==1.35.44
Requires-Dist: mypy-boto3-ecr==1.35.21
Requires-Dist: pytz==2024.2
Requires-Dist: structlog==24.4.0
Requires-Dist: types-pytz==2024.2.0.20241003
Provides-Extra: cli
Requires-Dist: pyyaml==6.0.2; extra == 'cli'
Requires-Dist: types-pyyaml==6.0.12.20240917; extra == 'cli'
Provides-Extra: dev
Requires-Dist: boto3==1.35.44; extra == 'dev'
Requires-Dist: build==1.2.2; extra == 'dev'
Requires-Dist: freezegun==1.5.1; extra == 'dev'
Requires-Dist: mock==5.1.0; extra == 'dev'
Requires-Dist: moto==5.0.17; extra == 'dev'
Requires-Dist: mypy-boto3-ecr==1.35.21; extra == 'dev'
Requires-Dist: pre-commit==3.8.0; extra == 'dev'
Requires-Dist: pytest==8.3.3; extra == 'dev'
Requires-Dist: pytz==2024.2; extra == 'dev'
Requires-Dist: structlog==24.4.0; extra == 'dev'
Requires-Dist: toml==0.10.2; extra == 'dev'
Requires-Dist: twine==5.1.1; extra == 'dev'
Requires-Dist: wheel-inspect==1.7.1; extra == 'dev'
Requires-Dist: wheel==0.44.0; extra == 'dev'
